coredotseries/__init__.py
coredotseries/cli.py
coredotseries/series.py
coredotseries/util.py
coredotseries/version.py
tests/__init__.py
tests/test_series.py
coredotseries-0.1.8.dist-info/AUTHORS.md
coredotseries-0.1.8.dist-info/LICENSE
coredotseries-0.1.8.dist-info/METADATA
coredotseries-0.1.8.dist-info/WHEEL
coredotseries-0.1.8.dist-info/entry_points.txt
coredotseries-0.1.8.dist-info/top_level.txt
coredotseries-0.1.8.dist-info/RECORD
