Metadata-Version: 2.1
Name: coredotseries
Version: 0.1.8
Summary: Library for time series
Home-page: https://github.com/coredottoday/CoreDotSeries.git
Author: CoreDotToday
Author-email: engine@core.today
License: Apache Software License 2.0
Keywords: coredotseries
Platform: UNKNOWN
Classifier: Development Status :: 2 - Pre-Alpha
Classifier: Intended Audience :: Developers
Classifier: License :: OSI Approved :: Apache Software License
Classifier: Programming Language :: Python :: 3
Classifier: Programming Language :: Python :: 3.6
Classifier: Programming Language :: Python :: 3.7
Classifier: Programming Language :: Python :: 3.8
Requires-Python: >=3.6
License-File: LICENSE
License-File: AUTHORS.md
Requires-Dist: Click (>=7.1.2)
